termi/__init__.py
termi/cli.py
termi_copilot-0.1.0.dist-info/METADATA
termi_copilot-0.1.0.dist-info/WHEEL
termi_copilot-0.1.0.dist-info/entry_points.txt
termi_copilot-0.1.0.dist-info/licenses/LICENSE
termi_copilot-0.1.0.dist-info/RECORD
