Metadata-Version: 2.4
Name: termi-copilot
Version: 0.1.0
Summary: Local-LLM terminal copilot that turns natural language into shell commands.
Project-URL: Homepage, https://github.com/abhaymundhara/Termi
Project-URL: Issues, https://github.com/abhaymundhara/Termi/issues
Author-email: Abhay Mundhara <abhay.mundhara@gmail.com>
License: MIT License
License-File: LICENSE
Keywords: copilot,llm,ollama,terminal
Classifier: Environment :: Console
Classifier: License :: OSI Approved :: MIT License
Classifier: Operating System :: MacOS
Classifier: Operating System :: POSIX :: Linux
Classifier: Programming Language :: Python :: 3
Classifier: Programming Language :: Python :: 3.9
Classifier: Programming Language :: Python :: 3.10
Classifier: Programming Language :: Python :: 3.11
Classifier: Programming Language :: Python :: 3.12
Requires-Python: >=3.9
